discrape/ScrapeMembers.py
discrape/__init__.py
discrape-0.0.13.dist-info/METADATA
discrape-0.0.13.dist-info/WHEEL
discrape-0.0.13.dist-info/top_level.txt
discrape-0.0.13.dist-info/RECORD
