Metadata-Version: 2.1
Name: discrape
Version: 0.0.13
Summary: Python roject containing managing tools for scraping discord server members.
Author: Jimmy Networks
Author-email: <mail@mail.com>
Keywords: python,pip
Classifier: Development Status :: 1 - Planning
Classifier: Intended Audience :: Developers
Classifier: Programming Language :: Python :: 3
Classifier: Operating System :: Unix
Classifier: Operating System :: MacOS :: MacOS X
Classifier: Operating System :: Microsoft :: Windows
Requires-Dist: discord
Requires-Dist: pywin32
Requires-Dist: pyautogui
Requires-Dist: requests
